pointevector/irs990/__init__.py
pointevector/irs990/__main__.py
pointevector/irs990/cache.py
pointevector/irs990/config.py
pointevector/irs990/index.py
pointevector_irs990-0.0.8.dist-info/LICENSE
pointevector_irs990-0.0.8.dist-info/METADATA
pointevector_irs990-0.0.8.dist-info/WHEEL
pointevector_irs990-0.0.8.dist-info/top_level.txt
pointevector_irs990-0.0.8.dist-info/RECORD
