Metadata-Version: 2.1
Name: pointevector-irs990
Version: 0.0.8
Summary: UNKNOWN
Home-page: https://github.com/Pointe-Vector/xml_parser
Author: Andrew Hoekstra
Author-email: andrew@pointevector.com
License: UNKNOWN
Platform: UNKNOWN
License-File: LICENSE
Requires-Dist: pointevector-xmlparser
Requires-Dist: ruamel.yaml
Requires-Dist: typing-extensions
